automatic_file_manager/__init__.py
automatic_file_manager/automatic_file_manager.py
automatic_file_manager/common.py
automatic_file_manager/file.py
tests/__init__.py
tests/test_automatic_file_manager.py
automatic_file_manager-0.0.1.dist-info/LICENSE
automatic_file_manager-0.0.1.dist-info/METADATA
automatic_file_manager-0.0.1.dist-info/WHEEL
automatic_file_manager-0.0.1.dist-info/top_level.txt
automatic_file_manager-0.0.1.dist-info/RECORD
