Metadata-Version: 2.1
Name: automatic_file_manager
Version: 0.0.1
Summary: Automatic file manager
Home-page: https://github.com/youssefbriki1/automatic_file_manager
Author: Youssef Briki
Author-email: youssef.briki05@gmail.com
Classifier: Programming Language :: Python :: 3
Classifier: License :: OSI Approved :: MIT License
Classifier: Operating System :: OS Independent
Requires-Python: >=3.6
License-File: LICENSE
